holospy/__init__.py
holospy/conftest.py
holospy/hyperspy_extension.yaml
holospy/reconstruct.py
holospy/tools.py
holospy/data/00_ref_Vbp_130V_0V_bin2_crop.hdf5
holospy/data/01_holo_Vbp_130V_0V_bin2_crop.hdf5
holospy/data/__init__.py
holospy/signals/__init__.py
holospy/signals/hologram_image.py
holospy/tests/__init__.py
holospy/tests/test_non-uniform_not-implemented.py
holospy/tests/signals/__init__.py
holospy/tests/signals/test_hologram_image.py
holospy/tests/signals/test_hologram_image_statistics.py
holospy-0.3.dist-info/LICENSE
holospy-0.3.dist-info/METADATA
holospy-0.3.dist-info/WHEEL
holospy-0.3.dist-info/entry_points.txt
holospy-0.3.dist-info/top_level.txt
holospy-0.3.dist-info/RECORD
