Metadata-Version: 2.1
Name: holospy
Version: 0.3
Summary: Analysis of (off-axis) electron holography data with HyperSpy.
License: GNU GENERAL PUBLIC LICENSE
Project-URL: Homepage, https://hyperspy.org/holospy
Project-URL: Bug Reports, https://github.com/hyperspy/holospy/issues
Project-URL: Source, https://github.com/hyperspy/holospy
Keywords: python,hyperspy,data analysis,microscopy,electron microscopy,electron holography,Off-axis holography,STEM,TEM
Classifier: Development Status :: 4 - Beta
Classifier: Intended Audience :: Developers
Classifier: Intended Audience :: Science/Research
Classifier: Topic :: Software Development :: Libraries
Classifier: Topic :: Scientific/Engineering
Classifier: Topic :: Scientific/Engineering :: Physics
Classifier: License :: OSI Approved :: GNU General Public License v3 (GPLv3)
Classifier: Operating System :: OS Independent
Classifier: Programming Language :: Python :: 3.8
Classifier: Programming Language :: Python :: 3.9
Classifier: Programming Language :: Python :: 3.10
Classifier: Programming Language :: Python :: 3.11
Classifier: Programming Language :: Python :: 3.12
Requires-Python: >=3.8
License-File: LICENSE
Requires-Dist: hyperspy >=2.0rc0
Requires-Dist: numpy >=1.20.0
Requires-Dist: pint >=0.10
Requires-Dist: scipy >=1.5.0
Provides-Extra: dev
Requires-Dist: black ; extra == 'dev'
Requires-Dist: holospy[doc] ; extra == 'dev'
Requires-Dist: holospy[tests] ; extra == 'dev'
Provides-Extra: doc
Requires-Dist: numpydoc ; extra == 'doc'
Requires-Dist: pydata-sphinx-theme >=0.13 ; extra == 'doc'
Requires-Dist: sphinx ; extra == 'doc'
Requires-Dist: sphinx-design ; extra == 'doc'
Requires-Dist: sphinx-favicon ; extra == 'doc'
Requires-Dist: sphinxcontrib-towncrier ; extra == 'doc'
Requires-Dist: towncrier ; extra == 'doc'
Provides-Extra: tests
Requires-Dist: pytest ; extra == 'tests'
Requires-Dist: pytest-cov ; extra == 'tests'
Requires-Dist: setuptools-scm ; extra == 'tests'
